newenvreader.py
newenvreader-0.2.0.dist-info/LICENSE
newenvreader-0.2.0.dist-info/METADATA
newenvreader-0.2.0.dist-info/WHEEL
newenvreader-0.2.0.dist-info/RECORD
