Metadata-Version: 2.1
Name: newenvreader
Version: 0.2.0
Summary: 
Author: Ajay Karthik
Author-email: ajaykarthik.r23@gmail.com
Requires-Python: >=3.10,<4.0
Classifier: Programming Language :: Python :: 3
Classifier: Programming Language :: Python :: 3.10
Classifier: Programming Language :: Python :: 3.11
